README.md
agenda.py
colores.py
contacto.py
main.py
menus.py
setup.py
pyagenda.egg-info/PKG-INFO
pyagenda.egg-info/SOURCES.txt
pyagenda.egg-info/dependency_links.txt
pyagenda.egg-info/entry_points.txt
pyagenda.egg-info/top_level.txt