Metadata-Version: 1.0
Name: pyagenda
Version: 0.0.1b0
Summary: Administracion de contacos telefonicos.
Home-page: https://github.com/raudin17/pyagenda
Author: Raudin Moreno
Author-email: raudin247@gmail.com
License: License :: OSI Approved :: MIT License
Platform: UNKNOWN
